seeker/__init__.py
seeker/libseeker.a
seeker/seeker.1.0.0.cpython-36-linux.so
seeker/seeker.py
seeker/bin/coll
seeker/bin/coll-linux
seeker/scripts/collect.sh
seeker/scripts/darwin_seekeragg.sh
seeker/scripts/seekeragg.sh
insideopt_centos-0.0.4.dist-info/AUTHORS.rst
insideopt_centos-0.0.4.dist-info/LICENSE.rst
insideopt_centos-0.0.4.dist-info/METADATA
insideopt_centos-0.0.4.dist-info/WHEEL
insideopt_centos-0.0.4.dist-info/top_level.txt
insideopt_centos-0.0.4.dist-info/RECORD
