Metadata-Version: 2.1
Name: insideopt-centos
Version: 0.0.4
Summary: InsideOpt Seeker Distribution for CentOS
Author: Meinolf Sellmann
Author-email: info@insideopt.com
Keywords: insideopt,seeker,optimization
Classifier: Development Status :: 5 - Production/Stable
Classifier: Intended Audience :: Developers
Classifier: Natural Language :: English
Classifier: Programming Language :: Python :: 3.6
Requires-Python: >=3.6.0
License-File: LICENSE.rst
License-File: AUTHORS.rst
